{
  "parent": "chronosphere:story/us1/dimension_entry",
  "criteria": {
    "killed_clockwork_sentinel": {
      "trigger": "minecraft:player_killed_entity",
      "conditions": {
        "entity": {
          "type": "chronosphere:clockwork_sentinel"
        }
      }
    }
  },
  "display": {
    "icon": {
      "id": "chronosphere:ancient_gear"
    },
    "title": {
      "translate": "advancements.chronosphere.clockwork_sentinel_defeated.title"
    },
    "description": {
      "translate": "advancements.chronosphere.clockwork_sentinel_defeated.description"
    },
    "frame": "task",
    "show_toast": true,
    "announce_to_chat": false,
    "hidden": false
  }
}
