{
  "parent": "chronosphere:root",
  "criteria": {
    "has_time_hourglass": {
      "trigger": "minecraft:inventory_changed",
      "conditions": {
        "items": [
          {
            "items": [
              "chronosphere:time_hourglass"
            ]
          }
        ]
      }
    }
  },
  "display": {
    "icon": {
      "id": "chronosphere:time_hourglass"
    },
    "title": {
      "translate": "advancements.chronosphere.portal_creation.title"
    },
    "description": {
      "translate": "advancements.chronosphere.portal_creation.description"
    },
    "frame": "task",
    "show_toast": true,
    "announce_to_chat": false,
    "hidden": false
  }
}
